[
    {
        "id": 1,
        "url": "assets/images/ads/tech.jpeg",
        "discount": "20%"
    },
    {
        "id": 2,
        "url": "assets/images/ads/vetements.webp",
        "discount": "40%"
    },
    {
        "id": 3,
        "url": "assets/images/ads/boissons.jpeg",
        "discount": "5%"
    },
    {
        "id": 4,
        "url": "assets/images/ads/cuisine.webp",
        "discount": "30%"
    },
    {
        "id": 5,
        "url": "assets/images/ads/nettoyage.jpeg",
        "discount": "45%%"
    }
]